LICENSE
README.md
setup.cfg
setup.py
SRParser/SnortParser.py
SRParser/__init__.py
SRParser.egg-info/PKG-INFO
SRParser.egg-info/SOURCES.txt
SRParser.egg-info/dependency_links.txt
SRParser.egg-info/requires.txt
SRParser.egg-info/top_level.txt