Metadata-Version: 2.1
Name: SRParser
Version: 1.0.1
Summary: Parse and easily work with Snort rules.
Home-page: https://www.github.com/jrbrawner/SnortParser
Author: Joshua Brawner
Author-email: jrbbrawner@gmail.com
License: Apache Software License
Keywords: snort rule parser
Classifier: Development Status :: 3 - Alpha
Classifier: Topic :: Utilities
Classifier: License :: OSI Approved :: Apache Software License
Classifier: Programming Language :: Python :: 3
License-File: LICENSE
